sphinx_math_dollar/__init__.py
sphinx_math_dollar/_version.py
sphinx_math_dollar/extension.py
sphinx_math_dollar/math_dollar.py
sphinx_math_dollar/tests/__init__.py
sphinx_math_dollar/tests/test_extension.py
sphinx_math_dollar/tests/test_math_dollar.py
sphinx_math_dollar-1.2.1.dist-info/LICENSE
sphinx_math_dollar-1.2.1.dist-info/METADATA
sphinx_math_dollar-1.2.1.dist-info/WHEEL
sphinx_math_dollar-1.2.1.dist-info/top_level.txt
sphinx_math_dollar-1.2.1.dist-info/RECORD
