Metadata-Version: 2.1
Name: sphinx-math-dollar
Version: 1.2.1
Summary: Sphinx extension to let you write LaTeX math using $$
Home-page: https://github.com/sympy/sphinx-math-dollar/
Author: SymPy Development Team
Author-email: sympy@googlegroups.com
License: MIT
Platform: UNKNOWN
Classifier: Programming Language :: Python :: 3
Classifier: License :: OSI Approved :: MIT License
Classifier: Operating System :: OS Independent
Requires-Python: >=3.6
License-File: LICENSE
